{
  "ReRoutes": [
    {
      "DownstreamPathTemplate": "/{url}",
      "DownstreamScheme": "http",
      "DownstreamHostAndPorts": [
        {
          "Host": "localhost",
          "Port": 6801
        }
      ],
      "UpstreamPathTemplate": "/basics/{url}",
      "UpstreamHttpMethod": [ "Get", "Post", "Delete", "Put" ],
      //"ServiceName": "BasicsService",
      //"LoadBalancer": "RoundRobin",
      //"UseServiceDiscovery": true,
      "ReRouteIsCaseSensitive": false,
      "QoSOptions": {
        "ExceptionsAllowedBeforeBreaking": 3,
        "DurationOfBreak": 10,
        "TimeoutValue": 5000
      },
      "HttpHandlerOptions": {
        "AllowAutoRedirect": false,
        "UseCookieContainer": false,
        "UseTracing": false
      },
      "AuthenticationOptions": {
        "AuthenticationProviderKey": "",
        "AllowedScopes": []
      },
      "RateLimitOptions": {
        "ClientWhitelist": [ "admin" ],
        "EnableRateLimiting": true,
        "Period": "1m",
        "PeriodTimespan": 15,
        "Limit": 100
      }
    },
    {
      "DownstreamPathTemplate": "/{url}",
      "DownstreamScheme": "http",
      "DownstreamHostAndPorts": [
        {
          "Host": "localhost",
          "Port": 6802
        }
      ],
      "UpstreamPathTemplate": "/invoicing/{url}",
      "UpstreamHttpMethod": [ "Get", "Post", "Delete", "Put" ],
      //"ServiceName": "InvoicingService",
      //"LoadBalancer": "RoundRobin",
      //"UseServiceDiscovery": true,
      "ReRouteIsCaseSensitive": false,
      "QoSOptions": {
        "ExceptionsAllowedBeforeBreaking": 3,
        "DurationOfBreak": 10,
        "TimeoutValue": 5000
      },
      "HttpHandlerOptions": {
        "AllowAutoRedirect": false,
        "UseCookieContainer": false,
        "UseTracing": false
      },
      "AuthenticationOptions": {
        "AuthenticationProviderKey": "",
        "AllowedScopes": []
      },
      "RateLimitOptions": {
        "ClientWhitelist": [ "admin" ],
        "EnableRateLimiting": true,
        "Period": "1m",
        "PeriodTimespan": 15,
        "Limit": 100
      }
    },
    {
      "DownstreamPathTemplate": "/{url}",
      "DownstreamScheme": "http",
      "DownstreamHostAndPorts": [
        {
          "Host": "localhost",
          "Port": 6806
        }
      ],
      "UpstreamPathTemplate": "/authentication/{url}",
      "UpstreamHttpMethod": [ "Get", "Post","Delete","Put" ],
      //"ServiceName": "AuthenticationService",
      //"LoadBalancer": "RoundRobin",
      //"UseServiceDiscovery": true,
      "ReRouteIsCaseSensitive": false,
      "QoSOptions": {
        "ExceptionsAllowedBeforeBreaking": 3,
        "DurationOfBreak": 10,
        "TimeoutValue": 5000
      },
      "HttpHandlerOptions": {
        "AllowAutoRedirect": false,
        "UseCookieContainer": false,
        "UseTracing": false
      },
      "AuthenticationOptions": {
        "AuthenticationProviderKey": "",
        "AllowedScopes": []
      },
      "RateLimitOptions": {
        "ClientWhitelist": [ "admin" ],
        "EnableRateLimiting": true,
        "Period": "1m",
        "PeriodTimespan": 15,
        "Limit": 100
      }
    }

  ],
  "GlobalConfiguration": {
    "ServiceDiscoveryProvider": {
      "Host": "localhost",
      "Port": 8500
    },
    "RateLimitOptions": {
      "ClientIdHeader": "clientid",
      "QuotaExceededMessage": "access is denied",
      "DisableRateLimitHeaders": false
    } 
  }
}